bonsai_ml/__init__.py
bonsai_ml/bonsai_ml.py
bonsai_ml-0.0.7.dist-info/METADATA
bonsai_ml-0.0.7.dist-info/WHEEL
bonsai_ml-0.0.7.dist-info/top_level.txt
bonsai_ml-0.0.7.dist-info/RECORD
