Metadata-Version: 2.1
Name: bonsai-ml
Version: 0.0.7
Summary: bonsai
Home-page: https://github.com/bonsai-tree-model/bonsai
Author: MAPS
Author-email: dongguk.maps@gmail.com
Keywords: Decision Tree,DT
Classifier: Programming Language :: Python :: 3.8
Classifier: Programming Language :: Python :: 3.9
Requires-Python: >=3.8
Requires-Dist: numpy
Requires-Dist: pandas
Requires-Dist: scikit-learn
Requires-Dist: docplex
Requires-Dist: psutil
